simplespec/__init__.py
simplespec/builder.py
simplespec/common.py
simplespec/generator.py
simplespec/typing.py
simplespec/walker.py
simplespec-0.1.1.dist-info/METADATA
simplespec-0.1.1.dist-info/WHEEL
simplespec-0.1.1.dist-info/licenses/LICENSE
simplespec-0.1.1.dist-info/RECORD
