Metadata-Version: 2.4
Name: simplespec
Version: 0.1.1
Summary: Convert Python typing annotations, Pydantic v2 models, and dataclasses into a compact, human-readable schema
Project-URL: Homepage, https://github.com/denizkenan/simplespec
Project-URL: Documentation, https://github.com/denizkenan/simplespec#readme
Project-URL: Repository, https://github.com/denizkenan/simplespec.git
Project-URL: Issues, https://github.com/denizkenan/simplespec/issues
Project-URL: Changelog, https://github.com/denizkenan/simplespec/releases
Author-email: Kenan Deniz <kenan@logistica-os.com>
Maintainer-email: Kenan Deniz <kenan@logistica-os.com>
License: Apache-2.0
License-File: LICENSE
Keywords: dataclass,pydantic,schema,specification,type-analysis,typing
Classifier: Development Status :: 4 - Beta
Classifier: Intended Audience :: Developers
Classifier: License :: OSI Approved :: Apache Software License
Classifier: Operating System :: OS Independent
Classifier: Programming Language :: Python :: 3
Classifier: Programming Language :: Python :: 3.11
Classifier: Programming Language :: Python :: 3.12
Classifier: Topic :: Software Development :: Code Generators
Classifier: Topic :: Software Development :: Libraries :: Python Modules
Classifier: Typing :: Typed
Requires-Python: >=3.11
Requires-Dist: annotated-types>=0.6.0
Requires-Dist: pydantic>=2.0.0
Provides-Extra: dev
Requires-Dist: mypy>=1.0.0; extra == 'dev'
Requires-Dist: pre-commit>=3.0.0; extra == 'dev'
Requires-Dist: pytest-cov>=4.0.0; extra == 'dev'
Requires-Dist: pytest>=7.0.0; extra == 'dev'
Requires-Dist: ruff>=0.1.0; extra == 'dev'
Provides-Extra: test
Requires-Dist: pytest-cov>=4.0.0; extra == 'test'
Requires-Dist: pytest>=7.0.0; extra == 'test'
